Metadata-Version: 1.1
Name: sumha
Version: 0.1
Summary: The sumha...
Home-page: http://github.com/storborg/sumha
Author: Flying Circus
Author-email: flyingcircus@example.com
License: MIT
Keywords: sumha joke comedy flying circus
Platform: UNKNOWN
Classifier: Development Status :: 3 - Alpha
Classifier: License :: OSI Approved :: MIT License
Classifier: Programming Language :: Python :: 2.7
Classifier: Topic :: Text Processing :: Linguistic
